FABulous/FABulous.py
FABulous/FABulous_API.py
FABulous/FABulous_settings.py
FABulous/__init__.py
FABulous/custom_exception.py
FABulous/FABulous_CLI/FABulous_CLI.py
FABulous/FABulous_CLI/__init__.py
FABulous/FABulous_CLI/cmd_synthesis.py
FABulous/FABulous_CLI/helper.py
FABulous/fabric_cad/README.md
FABulous/fabric_cad/__init__.py
FABulous/fabric_cad/gen_bitstream_spec.py
FABulous/fabric_cad/gen_design_top_wrapper.py
FABulous/fabric_cad/gen_npnr_model.py
FABulous/fabric_definition/Bel.py
FABulous/fabric_definition/ConfigMem.py
FABulous/fabric_definition/Fabric.py
FABulous/fabric_definition/Gen_IO.py
FABulous/fabric_definition/Port.py
FABulous/fabric_definition/SuperTile.py
FABulous/fabric_definition/Tile.py
FABulous/fabric_definition/Wire.py
FABulous/fabric_definition/Yosys_obj.py
FABulous/fabric_definition/__init__.py
FABulous/fabric_definition/define.py
FABulous/fabric_files/__init__.py
FABulous/fabric_files/FABulous_project_template_common/fabric.csv
FABulous/fabric_files/FABulous_project_template_common/Fabric/gds_config.yaml
FABulous/fabric_files/FABulous_project_template_common/Test/.gitignore
FABulous/fabric_files/FABulous_project_template_common/Test/build_fabulous_fabric.tcl
FABulous/fabric_files/FABulous_project_template_common/Test/makehex.py
FABulous/fabric_files/FABulous_project_template_common/Tile/DSP/DSP.csv
FABulous/fabric_files/FABulous_project_template_common/Tile/DSP/gds_config.yaml
FABulous/fabric_files/FABulous_project_template_common/Tile/DSP/DSP_bot/DSP_bot.csv
FABulous/fabric_files/FABulous_project_template_common/Tile/DSP/DSP_bot/DSP_bot_switch_matrix.list
FABulous/fabric_files/FABulous_project_template_common/Tile/DSP/DSP_top/DSP_top.csv
FABulous/fabric_files/FABulous_project_template_common/Tile/DSP/DSP_top/DSP_top_switch_matrix.list
FABulous/fabric_files/FABulous_project_template_common/Tile/LUT4AB/LUT4AB.csv
FABulous/fabric_files/FABulous_project_template_common/Tile/LUT4AB/LUT4AB_ConfigMem.csv
fabulous_fpga-2.0.0b2.dist-info/licenses/LICENSE
fabulous_fpga-2.0.0b2.dist-info/METADATA
fabulous_fpga-2.0.0b2.dist-info/WHEEL
fabulous_fpga-2.0.0b2.dist-info/entry_points.txt
fabulous_fpga-2.0.0b2.dist-info/top_level.txt
fabulous_fpga-2.0.0b2.dist-info/RECORD
