Metadata-Version: 2.4
Name: FABulous-FPGA
Version: 2.0.0b2
Summary: FABulous FPGA Fabric generator
Author-email: "Jing, Nguyen, Bea, Bardia, Dirk" <dirk.koch@manchester.ac.uk>
License: Apache-2.0
Project-URL: Repository, https://github.com/FPGA-Research/FABulous
Project-URL: Documentation, https://fabulous.readthedocs.io
Project-URL: Releases, https://github.com/FPGA-Research/FABulous/releases
Project-URL: Issues, https://github.com/FPGA-Research/FABulous/issues
Project-URL: Discussions, https://github.com/FPGA-Research/FABulous/discussions
Classifier: Programming Language :: Python :: 3
Classifier: Programming Language :: Python :: 3.12
Classifier: License :: OSI Approved :: Apache Software License
Classifier: Operating System :: OS Independent
Requires-Python: >=3.12
License-File: LICENSE
Requires-Dist: python-dotenv>=1.0.0
Requires-Dist: loguru>=0.7.0
Requires-Dist: requests>=2.0.0
Requires-Dist: cmd2>=2
Requires-Dist: bitarray>=3.3.0
Requires-Dist: pydantic>=2.12.1
Requires-Dist: pydantic-settings>=2.10.1
Requires-Dist: packaging>=25.0
Requires-Dist: typer>=0.20.0
Requires-Dist: FABulous-bit-gen>=0.1.0
Requires-Dist: PyYAML>=6.0.0
Requires-Dist: click>=8.0.0
Requires-Dist: pyreadline3>=3.4.0; sys_platform == "win32"
Requires-Dist: gnureadline>=8.2.0; sys_platform != "win32"
Dynamic: license-file
